st_switcher/__init__.py
st_switcher/frontend/index.html
st_switcher/frontend/main.js
st_switcher/frontend/script.js
st_switcher/frontend/streamlit-component-lib.js
st_switcher/frontend/style.css
st_switcher-0.1.2.dist-info/LICENSE
st_switcher-0.1.2.dist-info/METADATA
st_switcher-0.1.2.dist-info/WHEEL
st_switcher-0.1.2.dist-info/top_level.txt
st_switcher-0.1.2.dist-info/RECORD
