Metadata-Version: 2.1
Name: st-switcher
Version: 0.1.2
Summary: Streamlit component that allows you to do X
Author: Abraão Andrade
Author-email: abraaolpandrade@gmail.com
Requires-Python: >=3.7
License-File: LICENSE
Requires-Dist: streamlit (>=1.2)
Requires-Dist: jinja2
